agi_med_ai_chat_manager/__init__.py
agi_med_ai_chat_manager/airi_entrypoint.py
agi_med_ai_chat_manager/base_chat.py
agi_med_ai_chat_manager/entrypoints.py
agi_med_ai_chat_manager/entrypoints_accessor.py
agi_med_ai_chat_manager/entrypoints_config.py
agi_med_ai_chat_manager/fusion_brain_entrypoint.py
agi_med_ai_chat_manager/gigachat_entrypoint.py
agi_med_ai_chat_manager/io_sugar.py
agi_med_ai_chat_manager/models.py
agi_med_ai_chat_manager/open_router_entrypoint.py
agi_med_ai_chat_manager/yandex_gpt_entrypoint.py
agi_med_ai_chat_manager-1.11.6.dist-info/METADATA
agi_med_ai_chat_manager-1.11.6.dist-info/WHEEL
agi_med_ai_chat_manager-1.11.6.dist-info/top_level.txt
agi_med_ai_chat_manager-1.11.6.dist-info/RECORD
