Metadata-Version: 2.4
Name: agi_med_ai_chat_manager
Version: 1.11.6
Summary: Ai chat managers for agi-med team
Author: AGI-MED-TEAM
Requires-Python: >=3.11
Requires-Dist: requests==2.32.3
Requires-Dist: gigachat==0.1.39.post1
Requires-Dist: tiktoken==0.8.0
Requires-Dist: openai==1.61.0
Requires-Dist: loguru~=0.7.2
